bytecli/__init__.py
bytecli/main.py
bytecli-0.2.2.dist-info/LICENSE
bytecli-0.2.2.dist-info/METADATA
bytecli-0.2.2.dist-info/WHEEL
bytecli-0.2.2.dist-info/entry_points.txt
bytecli-0.2.2.dist-info/RECORD
