Metadata-Version: 2.1
Name: bytecli
Version: 0.2.2
Summary: Bytesized Hosting CLI app to get information on your App Box
Home-page: https://pypi.org/project/bytecli
License: MIT
Author: Allan
Author-email: allanklp@gmail.com
Requires-Python: >=3.10,<4.0
Classifier: License :: OSI Approved :: MIT License
Classifier: Programming Language :: Python :: 3
Classifier: Programming Language :: Python :: 3.10
Classifier: Programming Language :: Python :: 3.11
Requires-Dist: requests (>=2.28.2,<3.0.0)
Requires-Dist: rich (>=13.3.4,<14.0.0)
Requires-Dist: typer (>=0.7.0,<0.8.0)
Project-URL: Repository, https://github.com/allankp/bytecli
